sfxcollectd/__init__.py
sfxcollectd/__main__.py
sfxcollectd/collectd.py
sfxcollectd/config.py
sfxcollectd/interface.py
sfxcollectd/runner.py
sfxcollectd/typesdb.py
sfxmonitor/__init__.py
sfxmonitor/__main__.py
sfxmonitor/datapoint.py
sfxmonitor/output.py
sfxmonitor/runner.py
sfxmonitor/simple.py
sfxrunner/__init__.py
sfxrunner/imports.py
sfxrunner/logs.py
sfxrunner/messages.py
sfxrunner/scheduler/__init__.py
sfxrunner/scheduler/interval.py
sfxrunner/scheduler/simple.py
sfxpython-0.5.3.dist-info/LICENSE
sfxpython-0.5.3.dist-info/METADATA
sfxpython-0.5.3.dist-info/WHEEL
sfxpython-0.5.3.dist-info/top_level.txt
sfxpython-0.5.3.dist-info/RECORD
